stratae/__init__.py
stratae/py.typed
stratae/cache/__init__.py
stratae/cache/cache.py
stratae/cache/memory.py
stratae/cache/thread.py
stratae/cache/util.py
stratae/context/__init__.py
stratae/context/context.py
stratae/depends/__init__.py
stratae/depends/_wrappers.py
stratae/depends/depends.py
stratae/depends/exceptions.py
stratae/depends/inject.py
stratae/depends/resolver.py
stratae/integrations/asgi.py
stratae/lifecycle/__init__.py
stratae/lifecycle/_context.py
stratae/lifecycle/_decorators.py
stratae/lifecycle/_scope.py
stratae/lifecycle/_wrappers.py
stratae/lifecycle/async_lifecycle.py
stratae/lifecycle/exceptions.py
stratae/lifecycle/lifecycle.py
stratae/lifecycle/manage.py
stratae-0.0.1a1.dist-info/METADATA
stratae-0.0.1a1.dist-info/WHEEL
stratae-0.0.1a1.dist-info/top_level.txt
stratae-0.0.1a1.dist-info/RECORD
