Metadata-Version: 2.4
Name: stratae
Version: 0.0.1a1
Summary: A toolkit of composable tools for dependency injection, lifecycle management, and more.
Author: Scott Wahl
License: MIT
Project-URL: Homepage, https://github.com/Eudaetics/stratae
Project-URL: Repository, https://github.com/Eudaetics/stratae
Project-URL: Issues, https://github.com/Eudaetics/stratae/issues
Classifier: Development Status :: 3 - Alpha
Classifier: Intended Audience :: Developers
Classifier: License :: OSI Approved :: MIT License
Classifier: Programming Language :: Python :: 3
Classifier: Programming Language :: Python :: 3.12
Classifier: Programming Language :: Python :: 3.13
Requires-Python: >=3.12
Provides-Extra: dev
Requires-Dist: pre-commit>=4.2.0; extra == "dev"
Requires-Dist: pyright>=1.1.403; extra == "dev"
Requires-Dist: ruff>=0.12.2; extra == "dev"
Provides-Extra: test
Requires-Dist: pytest>=8.4.1; extra == "test"
Requires-Dist: pytest-asyncio>=1.0.0; extra == "test"
Requires-Dist: pytest-cov>=6.1.1; extra == "test"
Requires-Dist: pytest-mock>=3.14.1; extra == "test"
Provides-Extra: asgi
Requires-Dist: httpx>=0.28.1; extra == "asgi"
Requires-Dist: fastapi>=0.100.0; extra == "asgi"
